asc/__init__.py
asc/asc.py
asc/asc.ui
asc/asc_qt.py
asc/compiler.py
asc/crash.py
asc/data/aicommands.txt
asc/data/aicommands_daniilS_1.txt
asc/data/aicommands_daniilS_2.txt
asc/data/aicommands_old.txt
asc/data/asc.png
asc/data/bscommands.txt
asc/data/canvas.pks
asc/data/commands.txt
asc/data/icon.svg
asc/data/pktext.tbl
asc/data/stdlib/std.rbh
asc/data/stdlib/stdabilities.rbh
asc/data/stdlib/stdargs.rbh
asc/data/stdlib/stdattacks.rbh
asc/data/stdlib/stdeffects.rbh
asc/data/stdlib/stditems.rbh
asc/data/stdlib/stdmoves.rbh
asc/data/stdlib/stdpoke.rbh
asc/data/stdlib/stdtypes.rbh
asc/decompiler.py
asc/operators.py
asc/pokecommands.py
asc/qtgui.py
asc/text_translate.py
asc/utils.py
red_alien-2.0.1.dist-info/entry_points.txt
red_alien-2.0.1.dist-info/LICENSE
red_alien-2.0.1.dist-info/WHEEL
red_alien-2.0.1.dist-info/METADATA
red_alien-2.0.1.dist-info/RECORD
