Metadata-Version: 2.1
Name: red-alien
Version: 2.0.1
Summary: A compiler/decompiler for the script system found in GBA pokemon games
Home-page: https://www.cosarara.me/redalien/
License: GPL-3.0+
Author: Jaume Delclòs Coll
Author-email: me@cosarara.me
Requires-Python: >=3,<4
Classifier: License :: OSI Approved :: GNU General Public License v3 or later (GPLv3+)
Classifier: Programming Language :: Python :: 3
Classifier: Programming Language :: Python :: 3.4
Classifier: Programming Language :: Python :: 3.5
Classifier: Programming Language :: Python :: 3.6
Classifier: Programming Language :: Python :: 3.7
Requires-Dist: PyQt5 (>=5,<6)
Requires-Dist: QScintilla (>=2,<3)
Project-URL: Documentation, https://www.cosarara.me/redalien/manual/
Project-URL: Repository, https://github.com/cosarara/red-alien
